design.sv
// Code your design here
module Dpram(
  input clk,                        // Clock signal
  input [9:0] add_read_p1,
  input [9:0] add_read_p2,
  input [9:0] add_write_p1,
  input [9:0] add_write_p2,
  input [15:0] input_data_p1,
  input [15:0] input_data_p2,
  input we_p1,
  input we_p2,
  input re_p1,
  input re_p2,
  output reg [15:0] output_data_p1,
  output reg [15:0] output_data_p2
);

  reg [15:0] RAM [0:2047];           // Memory array

  always @(posedge clk) begin
    // Handle read operations
    if (re_p1) begin
      output_data_p1 <= RAM[add_read_p1];
    end
    if (re_p2) begin
      output_data_p2 <= RAM[add_read_p2];
    end

    // Handle write operations with "last write wins" rule
    if (we_p1 && we_p2 && (add_write_p1 == add_write_p2)) begin
      // If both ports write to the same address, Port 2's data wins
      RAM[add_write_p2] <= input_data_p2;
    end else begin
      if (we_p1) begin
        RAM[add_write_p1] <= input_data_p1;
      end
      if (we_p2) begin
        RAM[add_write_p2] <= input_data_p2;
      end
    end
  end

endmodule

testbench.sv
// Code your testbench here
// or browse Examples
module Dpram_tb;

  // Inputs
  reg clk;
  reg [9:0] add_read_p1;
  reg [9:0] add_read_p2;
  reg [9:0] add_write_p1;
  reg [9:0] add_write_p2;
  reg [15:0] input_data_p1;
  reg [15:0] input_data_p2;
  reg we_p1;
  reg we_p2;
  reg re_p1;
  reg re_p2;

  // Outputs
  wire [15:0] output_data_p1;
  wire [15:0] output_data_p2;

  // Instantiate the Dpram module
  Dpram uut (
    .clk(clk),
    .add_read_p1(add_read_p1),
    .add_read_p2(add_read_p2),
    .add_write_p1(add_write_p1),
    .add_write_p2(add_write_p2),
    .input_data_p1(input_data_p1),
    .input_data_p2(input_data_p2),
    .we_p1(we_p1),
    .we_p2(we_p2),
    .re_p1(re_p1),
    .re_p2(re_p2),
    .output_data_p1(output_data_p1),
    .output_data_p2(output_data_p2)
  );

  // Clock generation
  initial begin
    clk = 0;
    forever #5 clk = ~clk;  // 10ns clock period
  end

  // Test stimulus
  initial begin
    // Initialize Inputs
    add_read_p1 = 0;
    add_read_p2 = 0;
    add_write_p1 = 0;
    add_write_p2 = 0;
    input_data_p1 = 0;
    input_data_p2 = 0;
    we_p1 = 0;
    we_p2 = 0;
    re_p1 = 0;
    re_p2 = 0;

    // Wait for the reset time
    #10;

    // Test 1: Write to Port 1 and Read from Port 1
    add_write_p1 = 10'b0000000001;
    input_data_p1 = 16'hAAAA;
    we_p1 = 1;
    #10 we_p1 = 0;

    add_read_p1 = 10'b0000000001;
    re_p1 = 1;
    #10 re_p1 = 0;

    // Test 2: Write to Port 2 and Read from Port 2
    add_write_p2 = 10'b0000000010;
    input_data_p2 = 16'h5555;
    we_p2 = 1;
    #10 we_p2 = 0;

    add_read_p2 = 10'b0000000010;
    re_p2 = 1;
    #10 re_p2 = 0;

    // Test 3: Write to Port 1 and Read from Port 2 (Port 1 to Port 2)
    add_write_p1 = 10'b0000000011;
    input_data_p1 = 16'h1234;
    we_p1 = 1;
    #10 we_p1 = 0;

    add_read_p2 = 10'b0000000011;
    re_p2 = 1;
    #10 re_p2 = 0;

    // Test 4: Write to Port 2 and Read from Port 1 (Port 2 to Port 1)
    add_write_p2 = 10'b0000000100;
    input_data_p2 = 16'h5678;
    we_p2 = 1;
    #10 we_p2 = 0;

    add_read_p1 = 10'b0000000100;
    re_p1 = 1;
    #10 re_p1 = 0;

    // Test 5: Simultaneous writes to the same location from both ports (last write wins)
    add_write_p1 = 10'b0000000101;
    add_write_p2 = 10'b0000000101;
    input_data_p1 = 16'h9ABC;
    input_data_p2 = 16'hDEF0;
    we_p1 = 1;
    we_p2 = 1;
    #10 we_p1 = 0;
    we_p2 = 0;

    add_read_p1 = 10'b0000000101;
    re_p1 = 1;
    #10 re_p1 = 0;

    // End the simulation
    #20 $finish;
  end

  // Monitor the signals
  initial begin
    $monitor("Time: %0t | we_p1: %b | we_p2: %b | re_p1: %b | re_p2: %b | add_write_p1: %h | add_write_p2: %h | input_data_p1: %h | input_data_p2: %h | output_data_p1: %h | output_data_p2: %h", 
             $time, we_p1, we_p2, re_p1, re_p2, add_write_p1, add_write_p2, input_data_p1, input_data_p2, output_data_p1, output_data_p2);
  end

  initial begin
    // Dump waves to a file for viewing in GTKWave or other waveform viewers
    $dumpfile("dpram_waveform.vcd");
    $dumpvars(0, Dpram_tb);
  end

endmodule

dpram_waveform.vcd
$date
	Thu Sep  5 10:56:59 2024
$end
$version
	Icarus Verilog
$end
$timescale
	1s
$end
$scope module Dpram_tb $end
$var wire 16 ! output_data_p2 [15:0] $end
$var wire 16 " output_data_p1 [15:0] $end
$var reg 10 # add_read_p1 [9:0] $end
$var reg 10 $ add_read_p2 [9:0] $end
$var reg 10 % add_write_p1 [9:0] $end
$var reg 10 & add_write_p2 [9:0] $end
$var reg 1 ' clk $end
$var reg 16 ( input_data_p1 [15:0] $end
$var reg 16 ) input_data_p2 [15:0] $end
$var reg 1 * re_p1 $end
$var reg 1 + re_p2 $end
$var reg 1 , we_p1 $end
$var reg 1 - we_p2 $end
$scope module uut $end
$var wire 10 . add_read_p1 [9:0] $end
$var wire 10 / add_read_p2 [9:0] $end
$var wire 10 0 add_write_p1 [9:0] $end
$var wire 10 1 add_write_p2 [9:0] $end
$var wire 1 ' clk $end
$var wire 16 2 input_data_p1 [15:0] $end
$var wire 16 3 input_data_p2 [15:0] $end
$var wire 1 * re_p1 $end
$var wire 1 + re_p2 $end
$var wire 1 , we_p1 $end
$var wire 1 - we_p2 $end
$var reg 16 4 output_data_p1 [15:0] $end
$var reg 16 5 output_data_p2 [15:0] $end
$upscope $end
$upscope $end
$enddefinitions $end
$comment Show the parameter values. $end
$dumpall
$end
#0
$dumpvars
bx 5
bx 4
b0 3
b0 2
b0 1
b0 0
b0 /
b0 .
0-
0,
0+
0*
b0 )
b0 (
0'
b0 &
b0 %
b0 $
b0 #
bx "
bx !
$end
#5
1'
#10
0'
1,
b1010101010101010 (
b1010101010101010 2
b1 %
b1 0
#15
1'
#20
0'
1*
b1 #
b1 .
0,
#25
b1010101010101010 "
b1010101010101010 4
1'
#30
0'
1-
b101010101010101 )
b101010101010101 3
b10 &
b10 1
0*
#35
1'
#40
0'
1+
b10 $
b10 /
0-
#45
b101010101010101 !
b101010101010101 5
1'
#50
0'
1,
b1001000110100 (
b1001000110100 2
b11 %
b11 0
0+
#55
1'
#60
0'
1+
b11 $
b11 /
0,
#65
b1001000110100 !
b1001000110100 5
1'
#70
0'
1-
b101011001111000 )
b101011001111000 3
b100 &
b100 1
0+
#75
1'
#80
0'
1*
b100 #
b100 .
0-
#85
b101011001111000 "
b101011001111000 4
1'
#90
0'
1-
1,
b1101111011110000 )
b1101111011110000 3
b1001101010111100 (
b1001101010111100 2
b101 &
b101 1
b101 %
b101 0
0*
#95
1'
#100
0'
1*
b101 #
b101 .
0-
0,
#105
b1101111011110000 "
b1101111011110000 4
1'
#110
0'
0*
